COPYING
FileDropper.py
MANIFEST.in
cron-ffx-backup.sh
ffx-backup.py
setup.py
FileDropper.egg-info/PKG-INFO
FileDropper.egg-info/SOURCES.txt
FileDropper.egg-info/dependency_links.txt
FileDropper.egg-info/requires.txt
FileDropper.egg-info/top_level.txt