Metadata-Version: 1.0
Name: FileDropper
Version: 0.2
Summary: Easy access to FileDropper.com
Home-page: http://wiki.schnouki.net/dev:filedropper
Author: Thomas Jost
Author-email: thomas.jost@gmail.com
License: ISC
Download-URL: http://dev.schnouki.net/filedropper/FileDropper-0.2.tar.gz
Platform: Python 2.6
Classifier: Development Status :: 4 - Beta
Classifier: Environment :: Console
Classifier: Environment :: Web Environment
Classifier: Intended Audience :: Developers
Classifier: Intended Audience :: System Administrators
Classifier: License :: OSI Approved :: BSD License
Classifier: Operating System :: OS Independent
Classifier: Programming Language :: Python :: 2.6
Classifier: Topic :: Communications :: File Sharing
Classifier: Topic :: Internet :: WWW/HTTP
Classifier: Topic :: Software Development :: Libraries :: Python Modules
